n8n_mcp/__init__.py
n8n_mcp/__main__.py
n8n_mcp/client.py
n8n_mcp/custom_tools.py
n8n_mcp/openapi_spec.json
n8n_mcp/swagger.js
n8n_mcp_server-0.1.12.dist-info/licenses/LICENSE
n8n_mcp_server-0.1.12.dist-info/METADATA
n8n_mcp_server-0.1.12.dist-info/WHEEL
n8n_mcp_server-0.1.12.dist-info/entry_points.txt
n8n_mcp_server-0.1.12.dist-info/top_level.txt
n8n_mcp_server-0.1.12.dist-info/RECORD
