Metadata-Version: 2.4
Name: n8n-mcp-server
Version: 0.1.12
Summary: MCP server for n8n workflow automation
Author: n8n MCP Server Contributors
License: MIT
Project-URL: Homepage, https://github.com/andrewlwn77/n8n-mcp-server
Project-URL: Documentation, https://github.com/andrewlwn77/n8n-mcp-server#readme
Project-URL: Repository, https://github.com/andrewlwn77/n8n-mcp-server.git
Project-URL: Issues, https://github.com/andrewlwn77/n8n-mcp-server/issues
Keywords: n8n,mcp,automation,workflow,api
Classifier: Development Status :: 4 - Beta
Classifier: Intended Audience :: Developers
Classifier: License :: OSI Approved :: MIT License
Classifier: Programming Language :: Python :: 3
Classifier: Programming Language :: Python :: 3.8
Classifier: Programming Language :: Python :: 3.9
Classifier: Programming Language :: Python :: 3.10
Classifier: Programming Language :: Python :: 3.11
Classifier: Programming Language :: Python :: 3.12
Classifier: Topic :: Software Development :: Libraries :: Python Modules
Classifier: Topic :: System :: Distributed Computing
Requires-Python: >=3.8
License-File: LICENSE
Requires-Dist: fastmcp>=0.1.0
Requires-Dist: httpx>=0.25.0
Requires-Dist: python-dotenv>=1.0.0
Dynamic: license-file
